bputils/__init__.py
bputils/server.py
bputils-0.1.0.dist-info/WHEEL
bputils-0.1.0.dist-info/METADATA
bputils-0.1.0.dist-info/RECORD
