Metadata-Version: 2.1
Name: bputils
Version: 0.1.0
Summary: BP utils
License: MIT
Author: yokotoka
Author-email: hey@yokotoka.is
Requires-Python: >=3.7,<4.0
Classifier: License :: OSI Approved :: MIT License
Classifier: Programming Language :: Python :: 3
Classifier: Programming Language :: Python :: 3.7
Requires-Dist: grpcio (>=1.22,<2.0)
Requires-Dist: grpcio-tools (>=1.22,<2.0)
Requires-Dist: grpclib (>=0.2.5,<0.3.0)
Requires-Dist: protobuf (>=3.8,<4.0)
Requires-Dist: python-dotenv (>=0.10.3,<0.11.0)
